[
  {
    "ci": "85031412334",
    "nombre": "Ana",
    "apellidos": "Pérez García",
    "direccion": "Calle 12 No. 34",
    "edad": 32,
    "provincia": "HAB",
    "telefono": "53456789"
  },
  {
    "ci": "90102553678",
    "nombre": "Juan",
    "apellidos": "Martínez Rodríguez",
    "direccion": "Avenida 5ta No. 12",
    "edad": 28,
    "provincia": "PRI",
    "telefono": "59876543"
  },
  {
    "ci": "00051234536",
    "nombre": "María",
    "apellidos": "González López",
    "direccion": "Callejón del Carmen No. 1",
    "edad": 22,
    "provincia": "MTZ",
    "telefono": "55432109"
  },
  {
    "ci": "75112045367",
    "nombre": "Pedro",
    "apellidos": "Díaz Hernández",
    "direccion": "Reparto Alamar No. 54",
    "edad": 45,
    "provincia": "CFG",
    "telefono": "52345678"
  },
  {
    "ci": "60080512334",
    "nombre": "Rosa",
    "apellidos": "Fernández Pérez",
    "direccion": "Calle 8 No. 12",
    "edad": 60,
    "provincia": "VCL",
    "telefono": "51234567"
  },
  {
    "ci": "05021478390",
    "nombre": "Miguel",
    "apellidos": "Sánchez Rodríguez",
    "direccion": "Reparto El Vedado No. 12",
    "edad": 17,
    "provincia": "SSP",
    "telefono": "59876543"
  },
  {
    "ci": "80123156783",
    "nombre": "Laura",
    "apellidos": "González Díaz",
    "direccion": "Calle 100 No. 12",
    "edad": 40,
    "provincia": "CAV",
    "telefono": "53456789"
  },
  {
    "ci": "95090123435",
    "nombre": "David",
    "apellidos": "Pérez Martínez",
    "direccion": "Reparto Cubanacán No. 12",
    "edad": 25,
    "provincia": "CMG",
    "telefono": "55432109"
  },
  {
    "ci": "10041567893",
    "nombre": "Camila",
    "apellidos": "López Hernández",
    "direccion": "Calle 23 No. 12",
    "edad": 12,
    "provincia": "LTU",
    "telefono": "52345678"
  },
  {
    "ci": "70062012334",
    "nombre": "Jorge",
    "apellidos": "García Rodríguez",
    "direccion": "Reparto Miramar No. 12",
    "edad": 50,
    "provincia": "GRA",
    "telefono": "51234567"
  }
]